paiss/__init__.py
paiss-0.0.0.dist-info/LICENSE
paiss-0.0.0.dist-info/METADATA
paiss-0.0.0.dist-info/WHEEL
paiss-0.0.0.dist-info/top_level.txt
paiss-0.0.0.dist-info/RECORD
