Metadata-Version: 2.1
Name: paiss
Version: 0.0.0
Summary: Paiss is a library for efficient similarity search for pictures
Home-page: https://github.com/kenblikylee/paiss
Author: kenbliky
Author-email: leebenw@126.com
License: UNKNOWN
Platform: UNKNOWN
Classifier: Programming Language :: Python :: 3
Classifier: License :: OSI Approved :: MIT License
Classifier: Operating System :: OS Independent
